{
	"characteristics": [
		{
			"id": 0,
			"min": 0,
			"max": 100,
			"name": "vitality",
			"definition": "PointsDeVie",
			"type": "type",
			"precision": 1,
			"modif":true
		},
		{
			"id": 1,
			"min": 0,
			"max": 1,
			"name": "gender",
			"definition": "Genre",
			"type": "type",
			"precision": 1,
			"modif":true
		},
		{
			"id": 2,
			"min": 0,
			"max": 100,
			"name": "Age",
			"definition": "Age",
			"type": "type",
			"precision": 1,
			"modif":true
		},
		{
			"id": 3,
			"min": 0,
			"max": 100,
			"name": "Agressiveness",
			"definition": "Agressivité",
			"type": "type",
			"precision": 1,
			"modif":true
		},
		{
			"id": 4,
			"min": 0,
			"max": 100,
			"name": "Fitness",
			"definition": "Forme",
			"type": "type",
			"precision": 1,
			"modif":true
		},
		{
			"id": 5,
			"min": 0,
			"max": 100,
			"name": "Satiety",
			"definition": "Faim",
			"type": "type",
			"precision": 1,
			"modif":true
		},
		{
			"id": 6,
			"min": 0,
			"max": 100,
			"name": "StatietyTreshold",
			"definition": "SeuilFaim",
			"type": "type",
			"precision": 1,
			"modif":true
		},
		{
			"id": 7,
			"min": 0,
			"max": 100,
			"name": "Reflex",
			"definition": "Reflexes",
			"type": "type",
			"precision": 1,
			"modif":true
		},
		{
			"id": 8,
			"min": 0,
			"max": 100,
			"name": "Perception",
			"definition": "Perception",
			"type": "type",
			"precision": 1,
			"modif":true
		},
		{
			"id": 9,
			"min": 0,
			"max": 100,
			"name": "Independence",
			"definition": "Indépendance",
			"type": "type",
			"precision": 1,
			"modif":true
		},
		{
			"id": 10 ,
			"min": 0,
			"max": 100,
			"name": "Charisma",
			"definition": "Charisme",
			"type": "type",
			"precision": 1,
			"modif":true
		},
		{
			"id": 11,
			"min": 0,
			"max": 100,
			"name": "Capacity",
			"definition": "Capacité",
			"type": "type",
			"precision": 1,
			"modif":true
		},
		{
			"id": 12,
			"min": 0,
			"max": 100,
			"name": "Stamina",
			"definition": "Endurance",
			"type": "type",
			"precision": 1,
			"modif":true
		},
		{
			"id": 13,
			"min": 0,
			"max": 100,
			"name": "StaminaThreshold",
			"definition": "SeuilEndurance",
			"type": "type",
			"precision": 1,
			"modif":true
		},
		{
			"id": 14,
			"min": 0,
			"max": 100,
			"name": "Sanity",
			"definition": "Sanité",
			"type": "type",
			"precision": 1,
			"modif":true
		},
		{
			"id": 15,
			"min": 10,
			"max": 50,
			"name": "RespawnRate",
			"definition": "TauxRepop",
			"type": "type",
			"precision": 1,
			"modif":true
		},
		{
			"id": 16,
			"min": 0,
			"max": 15,
			"name": "RespawnValue",
			"definition": "ValeurRepop",
			"type": "type",
			"precision": 1,
			"modif":true
		},
		{
			"id": 17,
			"min": 0,
			"max": 3,
			"name": "Orientation",
			"definition": "Orientation",
			"type": "type",
			"precision": 1,
			"modif":true
		},
		{
			"id": 18,
			"min": 0,
			"max": 100,
			"name": "StructuralPoints",
			"definition": "PointsdeStructure",
			"type": "type",
			"precision": 1,
			"modif":true
		},
		{
			"id": 19,
			"min": 0,
			"max": 100,
			"name": "Weight",
			"definition": "PoidsItem",
			"type": "type",
			"precision": 1,
			"modif":true
		},
		{
			"id": 20,
			"min": 300,
			"max": 600,
			"name": "MaxResStock",
			"definition": "Le stock maximum d'une ressource",
			"type": "unite",
			"precision": 1,
			"modif":true
		},
		{
			"id": 21,
			"min": 5,
			"max": 15,
			"name": "SatietyDecade",
			"definition": "Le taux de décadence de la Satiety d'un agent",
			"type": "tours",
			"precision": 1,
			"modif":true
		},
		{
			"id": 22,
			"min": 1,
			"max": 10,
			"name": "SatietyDecadeValue",
			"definition": "La valeur de décadence de la Satiety d'un agent",
			"type": "unite",
			"precision": 1,
			"modif":true
		},
		{
			"id": 23,
			"min": 5,
			"max": 15,
			"name": "StaminaDecade",
			"definition": "Le taux de décadence de la Stamina d'un agent",
			"type": "tours",
			"precision": 1,
			"modif":true
		},
		{
			"id": 24,
			"min": 1,
			"max": 10,
			"name": "StaminaDecadeValue",
			"definition": "La valeur de décadence de la Stamina d'un agent",
			"type": "unite",
			"precision": 1,
			"modif":true
		}
	]
}
